LICENSE.txt
MANIFEST.in
README.md
setup.py
Hjun2/__init__.py
Hjun2/hj.py
Hjun2/test_pack.py
Hjun2.egg-info/PKG-INFO
Hjun2.egg-info/SOURCES.txt
Hjun2.egg-info/dependency_links.txt
Hjun2.egg-info/entry_points.txt
Hjun2.egg-info/requires.txt
Hjun2.egg-info/top_level.txt