Metadata-Version: 1.0
Name: Hjun2
Version: 0.1.0
Summary: hjun machine learning
Home-page: UNKNOWN
Author: Hjun
Author-email: hjun.jeon@samsung.com
License: UNKNOWN
Platform: UNKNOWN
